mlwizard/__init__.py
mlwizard/chatbot.py
mlwizards/__init__.py
mlwizards/chatbot.py
tests/__init__.py
tests/test_chatbot.py
mlwizards-0.1.1.dist-info/LICENSE
mlwizards-0.1.1.dist-info/METADATA
mlwizards-0.1.1.dist-info/WHEEL
mlwizards-0.1.1.dist-info/entry_points.txt
mlwizards-0.1.1.dist-info/top_level.txt
mlwizards-0.1.1.dist-info/RECORD
