Metadata-Version: 2.1
Name: mlwizards
Version: 0.1.1
Summary: A simple library for chatbots and model finetuning using OpenAI
Author: Yvon Kim
Author-email: kmyn7up@gmail.com
Classifier: Programming Language :: Python :: 3
Classifier: Programming Language :: Python :: 3.6
Classifier: Programming Language :: Python :: 3.7
Classifier: Programming Language :: Python :: 3.8
Classifier: Programming Language :: Python :: 3.9
Classifier: Programming Language :: Python :: 3.10
Classifier: License :: OSI Approved :: MIT License
Classifier: Operating System :: OS Independent
Requires-Python: >=3.6
License-File: LICENSE
Requires-Dist: openai
Requires-Dist: pytesseract
Requires-Dist: pdf2image
Requires-Dist: pillow
Requires-Dist: googlesearch-python
Requires-Dist: requests
Requires-Dist: beautifulsoup4
